code_printer/__init__.py
code_printer/cli.py
code_printer/core.py
code_printer-1.0.3.dist-info/METADATA
code_printer-1.0.3.dist-info/WHEEL
code_printer-1.0.3.dist-info/entry_points.txt
code_printer-1.0.3.dist-info/top_level.txt
code_printer-1.0.3.dist-info/RECORD
