Metadata-Version: 2.4
Name: code-printer
Version: 1.0.3
Summary: A global Python package to print predefined code snippets
Home-page: https://github.com/MrPhantom2325/code-printer.git
Author: Shriyans
Author-email: Shriyans <shriyans.work2325@gmail.com>
License: MIT
Project-URL: Repository, https://github.com/MrPhantom2325/code-printer.git
Classifier: Development Status :: 4 - Beta
Classifier: Intended Audience :: Developers
Classifier: License :: OSI Approved :: MIT License
Classifier: Operating System :: OS Independent
Classifier: Programming Language :: Python :: 3
Requires-Python: >=3.7
Dynamic: author
Dynamic: home-page
Dynamic: requires-python
